README.rst
setup.py
karlooper/__init__.py
karlooper.egg-info/PKG-INFO
karlooper.egg-info/SOURCES.txt
karlooper.egg-info/dependency_links.txt
karlooper.egg-info/requires.txt
karlooper.egg-info/top_level.txt
karlooper/autoreload/__init__.py
karlooper/config/__init__.py
karlooper/config/config.py
karlooper/coroutine/__init__.py
karlooper/coroutine/coroutine_pool.py
karlooper/escape/__init__.py
karlooper/http_parser/__init__.py
karlooper/http_parser/http_parser.py
karlooper/logger/__init__.py
karlooper/logger/log.conf
karlooper/logger/logger.py
karlooper/router/__init__.py
karlooper/router/router.py
karlooper/template/__init__.py
karlooper/utils/__init__.py
karlooper/utils/base64encrypt.py
karlooper/utils/des_encrypt.py
karlooper/utils/encrypt.py
karlooper/utils/encryption.c
karlooper/utils/encryption.pyi
karlooper/utils/http_utils.py
karlooper/utils/parse_command_line.py
karlooper/web/__async_core_server.py
karlooper/web/__init__.py
karlooper/web/application.py
karlooper/web/http_connection.py
karlooper/web/http_io_buffer.py
karlooper/web/http_io_routine_pool.py
karlooper/web/request.py
karlooper/web/response.py
karlooper/web/statics.py