Metadata-Version: 1.1
Name: karlooper
Version: 0.7.2
Summary: karloop plus micro-framework
Home-page: https://github.com/karldoenitz/karlooper
Author: lizhihao
Author-email: karlvorndoenitz@gmail.com
License: MIT
Platform: UNKNOWN
Classifier: Environment :: Web Environment
Classifier: Intended Audience :: Developers
Classifier: Operating System :: OS Independent
Classifier: Programming Language :: Python :: 2
Classifier: Programming Language :: Python :: 2.6
Classifier: Programming Language :: Python :: 2.7
Classifier: Programming Language :: Python :: 3.5
